cli_game/__init__.py
cli_game/_version.py
cli_game/game.py
cli_sliding_puzzle-0.1.4.post0.dist-info/METADATA
cli_sliding_puzzle-0.1.4.post0.dist-info/WHEEL
cli_sliding_puzzle-0.1.4.post0.dist-info/entry_points.txt
cli_sliding_puzzle-0.1.4.post0.dist-info/top_level.txt
cli_sliding_puzzle-0.1.4.post0.dist-info/RECORD
