Metadata-Version: 2.1
Name: cli-sliding-puzzle
Version: 0.1.4.post0
Summary: A CLI sliding puzzle game
Author-email: Wade Wegner <wade.wegner@gmail.com>
License: MIT
Keywords: game,puzzle,cli
Classifier: Programming Language :: Python :: 3
Classifier: License :: OSI Approved :: MIT License
Classifier: Operating System :: OS Independent
Requires-Python: >=3.7
Requires-Dist: windows-curses ; platform_system == "Windows"
